bootstrap/__init__.py
bootstrap/static/bootstrap/css/bootstrap-grid.css
bootstrap/static/bootstrap/css/bootstrap-grid.css.map
bootstrap/static/bootstrap/css/bootstrap-grid.min.css
bootstrap/static/bootstrap/css/bootstrap-grid.min.css.map
bootstrap/static/bootstrap/css/bootstrap-reboot.css
bootstrap/static/bootstrap/css/bootstrap-reboot.css.map
bootstrap/static/bootstrap/css/bootstrap-reboot.min.css
bootstrap/static/bootstrap/css/bootstrap-reboot.min.css.map
bootstrap/static/bootstrap/css/bootstrap.css
bootstrap/static/bootstrap/css/bootstrap.css.map
bootstrap/static/bootstrap/css/bootstrap.min.css
bootstrap/static/bootstrap/css/bootstrap.min.css.map
bootstrap/static/bootstrap/js/bootstrap.bundle.js
bootstrap/static/bootstrap/js/bootstrap.bundle.js.map
bootstrap/static/bootstrap/js/bootstrap.bundle.min.js
bootstrap/static/bootstrap/js/bootstrap.bundle.min.js.map
bootstrap/static/bootstrap/js/bootstrap.js
bootstrap/static/bootstrap/js/bootstrap.js.map
bootstrap/static/bootstrap/js/bootstrap.min.js
bootstrap/static/bootstrap/js/bootstrap.min.js.map
bootstrap/static/bootstrap/js/jquery.js
bootstrap/static/bootstrap/js/jquery.min.js
bootstrap/static/bootstrap/js/jquery.min.map
django_bootstrap_static-4.2.1.dist-info/DESCRIPTION.rst
django_bootstrap_static-4.2.1.dist-info/METADATA
django_bootstrap_static-4.2.1.dist-info/RECORD
django_bootstrap_static-4.2.1.dist-info/WHEEL
django_bootstrap_static-4.2.1.dist-info/metadata.json
django_bootstrap_static-4.2.1.dist-info/top_level.txt
fontawesome/__init__.py
fontawesome/static/fontawesome/css/all.css
fontawesome/static/fontawesome/css/all.min.css
fontawesome/static/fontawesome/css/brands.css
fontawesome/static/fontawesome/css/brands.min.css
fontawesome/static/fontawesome/css/fontawesome.css
fontawesome/static/fontawesome/css/fontawesome.min.css
fontawesome/static/fontawesome/css/regular.css
fontawesome/static/fontawesome/css/regular.min.css
fontawesome/static/fontawesome/css/solid.css
fontawesome/static/fontawesome/css/solid.min.css
fontawesome/static/fontawesome/css/svg-with-js.css
fontawesome/static/fontawesome/css/svg-with-js.min.css
fontawesome/static/fontawesome/css/v4-shims.css
fontawesome/static/fontawesome/css/v4-shims.min.css
fontawesome/static/fontawesome/js/all.js
