Metadata-Version: 1.1
Name: django-bootstrap-static
Version: 4.2.1
Summary: A collection of Bootstrap static files.
Home-page: http://github.com/bittner/django-bootstrap-static
Author: Peter Bittner
Author-email: django@bittner.it
License: MIT
Keywords: django,staticfiles,bootstrap,jquery,fontawesome
Platform: UNKNOWN
Classifier: Development Status :: 5 - Production/Stable
Classifier: Environment :: Web Environment
Classifier: Intended Audience :: Developers
Classifier: Natural Language :: English
Classifier: Operating System :: OS Independent
Classifier: Framework :: Django
Classifier: Programming Language :: Python
Classifier: Programming Language :: Python :: 2
Classifier: Programming Language :: Python :: 3
Classifier: Topic :: Internet :: WWW/HTTP :: Dynamic Content :: CGI Tools/Libraries
Classifier: Topic :: Utilities
Classifier: License :: OSI Approved :: MIT License
